python_rush-1.0.0.dist-info/DESCRIPTION.rst
python_rush-1.0.0.dist-info/METADATA
python_rush-1.0.0.dist-info/RECORD
python_rush-1.0.0.dist-info/WHEEL
python_rush-1.0.0.dist-info/metadata.json
python_rush-1.0.0.dist-info/top_level.txt
rush/__init__.py
rush/tests.py
